seven_shop_studio/__init__.py
seven_shop_studio/route.py
seven_shop_studio/handlers/__init__.py
seven_shop_studio/handlers/seven_base.py
seven_shop_studio/handlers/server/__init__.py
seven_shop_studio/handlers/server/category.py
seven_shop_studio/handlers/server/coupon.py
seven_shop_studio/handlers/server/goods.py
seven_shop_studio/handlers/server/order.py
seven_shop_studio/handlers/server/series.py
seven_shop_studio/handlers/server/shop.py
seven_shop_studio/libs/__init__.py
seven_shop_studio/libs/customize/__init__.py
seven_shop_studio/libs/customize/coupon_helper.py
seven_shop_studio/libs/customize/data_helper.py
seven_shop_studio/libs/customize/order_helper.py
seven_shop_studio/libs/customize/wechat_helper.py
seven_shop_studio/models/__init__.py
seven_shop_studio/models/db_models/__init__.py
seven_shop_studio/models/db_models/cart/__init__.py
seven_shop_studio/models/db_models/cart/cart_model.py
seven_shop_studio/models/db_models/cart/cart_model_ex.py
seven_shop_studio/models/db_models/coupon/__init__.py
seven_shop_studio/models/db_models/coupon/coupon_goods_model.py
seven_shop_studio/models/db_models/coupon/coupon_goods_model_ex.py
seven_shop_studio/models/db_models/coupon/coupon_grant_model.py
seven_shop_studio/models/db_models/coupon/coupon_grant_model_ex.py
seven_shop_studio/models/db_models/coupon/coupon_model.py
seven_shop_studio/models/db_models/coupon/coupon_model_ex.py
seven_shop_studio/models/db_models/coupon/coupon_record_model.py
seven_shop_studio/models/db_models/goods/__init__.py
seven_shop_studio/models/db_models/goods/goods_model.py
seven_shop_studio/models/db_models/goods/goods_model_ex.py
seven_shop_studio/models/db_models/goods/goods_recommend_model.py
seven_shop_studio/models/db_models/goods/goods_recommend_model_ex.py
seven_shop_studio/models/db_models/goods/goods_sku_model.py
seven_shop_studio/models/db_models/goods/goods_sku_model_ex.py
seven_shop_studio/models/db_models/inventory/__init__.py
seven_shop_studio-1.0.35.dist-info/LICENSE
seven_shop_studio-1.0.35.dist-info/METADATA
seven_shop_studio-1.0.35.dist-info/WHEEL
seven_shop_studio-1.0.35.dist-info/top_level.txt
seven_shop_studio-1.0.35.dist-info/RECORD
