Metadata-Version: 2.1
Name: seven-shop-studio
Version: 1.0.35
Summary: seven shop studio
Home-page: http://gitlab.tdtech.gao7.com/python/pypi_packages/seven_shop/seven_shop_studio
Author: seven
Author-email: tech@gao7.com
License: MIT
Platform: UNKNOWN
Classifier: Topic :: Software Development :: Libraries :: Python Modules
Classifier: Programming Language :: Python
Classifier: Programming Language :: Python :: 3.4
Classifier: Programming Language :: Python :: 3.5
Classifier: Programming Language :: Python :: 3.5
Classifier: Programming Language :: Python :: 3.6
Classifier: Programming Language :: Python :: 3.7
Classifier: Programming Language :: Python :: 3.8
Classifier: Programming Language :: Python :: 3.9
Classifier: Programming Language :: Python :: 3.10
Requires-Python: ~=3.4
Requires-Dist: seven-framework (>=1.1.31)
Requires-Dist: seven-studio (>=1.5.0)
